adafruit_mpl115a2.py
adafruit_circuitpython_mpl115a2-1.1.22.dist-info/licenses/LICENSE
adafruit_circuitpython_mpl115a2-1.1.22.dist-info/METADATA
adafruit_circuitpython_mpl115a2-1.1.22.dist-info/WHEEL
adafruit_circuitpython_mpl115a2-1.1.22.dist-info/top_level.txt
adafruit_circuitpython_mpl115a2-1.1.22.dist-info/RECORD
